xstatic/__init__.py
xstatic/pkg/__init__.py
xstatic/pkg/html5shiv/.DS_Store
xstatic/pkg/html5shiv/__init__.py
xstatic/pkg/html5shiv/data/.DS_Store
xstatic/pkg/html5shiv/data/js/.DS_Store
xstatic/pkg/html5shiv/data/js/html5shiv.min.js
xstatic_html5shiv-3.6.1.dist-info/METADATA
xstatic_html5shiv-3.6.1.dist-info/WHEEL
xstatic_html5shiv-3.6.1.dist-info/top_level.txt
xstatic_html5shiv-3.6.1.dist-info/RECORD
