Metadata-Version: 2.4
Name: XStatic-html5shiv
Version: 3.6.1
Summary: html5shiv 3.6 (XStatic packaging standard)
Home-page: https://github.com/aFarkas/html5shiv/
Maintainer: Raphael Jasjukaitis
Maintainer-email: webmaster@raphaa.de
License: (same as html5shiv)
Keywords: html5shiv xstatic
Platform: any
Requires-Dist: xstatic
Dynamic: description
Dynamic: home-page
Dynamic: keywords
Dynamic: license
Dynamic: maintainer
Dynamic: maintainer-email
Dynamic: platform
Dynamic: requires-dist
Dynamic: summary
